pygetindia/__init__.py
pygetindia/pygetindia.py
pygetindia-0.0.1.dist-info/METADATA
pygetindia-0.0.1.dist-info/WHEEL
pygetindia-0.0.1.dist-info/top_level.txt
pygetindia-0.0.1.dist-info/RECORD
