Metadata-Version: 2.1
Name: pygetindia
Version: 0.0.1
Summary: get all the states and cities of india
Author: UNshubh (UnOfficialShubh)
Author-email: <shubhashishpresent@gmail.com>
Keywords: python,india,states,cities,state,city
Classifier: Development Status :: 1 - Planning
Classifier: Intended Audience :: Developers
Classifier: Programming Language :: Python :: 3.10
Classifier: Operating System :: Unix
Classifier: Operating System :: MacOS :: MacOS X
Classifier: Operating System :: Microsoft :: Windows
